from_root/__init__.py
from_root/base.py
from_root/get_project_root.py
from_root/here.py
from_root/root.py
from_root-1.2.0.dist-info/LICENSE
from_root-1.2.0.dist-info/WHEEL
from_root-1.2.0.dist-info/METADATA
from_root-1.2.0.dist-info/RECORD
