Metadata-Version: 2.1
Name: from-root
Version: 1.2.0
Summary: Forget about working directory errors
Author: Eduard Kononov
Author-email: aduard.kononov@gmail.com
Requires-Python: >=3.7,<4.0
Classifier: License :: OSI Approved :: MIT License
Classifier: Operating System :: OS Independent
Classifier: Programming Language :: Python :: 3
Classifier: Programming Language :: Python :: 3.7
Classifier: Programming Language :: Python :: 3.8
Classifier: Programming Language :: Python :: 3.9
Classifier: Programming Language :: Python :: 3.10
Classifier: Programming Language :: Python :: 3.11
Classifier: Programming Language :: Python :: 3
Project-URL: GitHub, https://github.com/EduardKononov/from-root
